[{"fields":{"fldRAy7cHq2HLptEV":"Telephone/Cell Phone","fldAPU282Pp3dp9YW":["recF3zFKbY4wJ4P40"],"fld7TUYeH17YX6t0N":2026,"fldnEtJyU9t4Q91vq":"Budget","fldIngfMXZEpuSlVu":"Operating Expenses","fldJu5jjEXn4mMYSG":"Administrative","fldKCw72lO9e0WFuz":"7005","fldKtkY7NTlIHol07":"Frontier / AT&T","fldoKDNjWKF9G5QhM":760,"fld6GLkqY33kT0nEr":760,"fld0laRIRvKrLgieR":760,"fldQaEaLQpYkp02pC":760,"fldRbPDZriXyBT0xk":760,"fldpLdJF85G236uWz":760,"fldB978FBdF1cbkOz":760,"fldv6nDF3xptGKP4p":760,"fldv2HR9VxIAjDcMW":760,"flddqJsbfKVRQ5bZa":760,"fld0TUl79Wkn8iVBD":760,"fldKW4xf1jkVzRwy0":760}},{"fields":{"fldRAy7cHq2HLptEV":"Computer Hardware/Software","fldAPU282Pp3dp9YW":["recF3zFKbY4wJ4P40"],"fld7TUYeH17YX6t0N":2026,"fldnEtJyU9t4Q91vq":"Budget","fldIngfMXZEpuSlVu":"Operating Expenses","fldJu5jjEXn4mMYSG":"Administrative","fldKCw72lO9e0WFuz":"7006","fldKtkY7NTlIHol07":"NetImage, VTS, Building Engines","fldoKDNjWKF9G5QhM":820,"fld6GLkqY33kT0nEr":820,"fld0laRIRvKrLgieR":10585,"fldQaEaLQpYkp02pC":820,"fldRbPDZriXyBT0xk":12320,"fldpLdJF85G236uWz":1745,"fldB978FBdF1cbkOz":820,"fldv6nDF3xptGKP4p":820,"fldv2HR9VxIAjDcMW":1745,"flddqJsbfKVRQ5bZa":820,"fld0TUl79Wkn8iVBD":820,"fldKW4xf1jkVzRwy0":1745}},{"fields":{"fldRAy7cHq2HLptEV":"Cable/Internet","fldAPU282Pp3dp9YW":["recF3zFKbY4wJ4P40"],"fld7TUYeH17YX6t0N":2026,"fldnEtJyU9t4Q91vq":"Budget","fldIngfMXZEpuSlVu":"Operating Expenses","fldJu5jjEXn4mMYSG":"Administrative","fldKCw72lO9e0WFuz":"7007","fldKtkY7NTlIHol07":"Optimum","fldoKDNjWKF9G5QhM":1245,"fld6GLkqY33kT0nEr":1245,"fld0laRIRvKrLgieR":1245,"fldQaEaLQpYkp02pC":1245,"fldRbPDZriXyBT0xk":1245,"fldpLdJF85G236uWz":1245,"fldB978FBdF1cbkOz":1245,"fldv6nDF3xptGKP4p":1245,"fldv2HR9VxIAjDcMW":1245,"flddqJsbfKVRQ5bZa":1245,"fld0TUl79Wkn8iVBD":1245,"fldKW4xf1jkVzRwy0":1245}},{"fields":{"fldRAy7cHq2HLptEV":"Utilities - Electric","fldAPU282Pp3dp9YW":["recF3zFKbY4wJ4P40"],"fld7TUYeH17YX6t0N":2026,"fldnEtJyU9t4Q91vq":"Budget","fldIngfMXZEpuSlVu":"Operating Expenses","fldJu5jjEXn4mMYSG":"Utilities","fldKCw72lO9e0WFuz":"","fldKtkY7NTlIHol07":"","fldoKDNjWKF9G5QhM":8979.17,"fld6GLkqY33kT0nEr":-5367.08,"fld0laRIRvKrLgieR":5845.95,"fldQaEaLQpYkp02pC":-53.34,"fldRbPDZriXyBT0xk":-3124.34,"fldpLdJF85G236uWz":25472.08,"fldB978FBdF1cbkOz":15408.5,"fldv6nDF3xptGKP4p":6845.55,"fldv2HR9VxIAjDcMW":21218.83,"flddqJsbfKVRQ5bZa":29944.48,"fld0TUl79Wkn8iVBD":21737.55,"fldKW4xf1jkVzRwy0":14339.73}},{"fields":{"fldRAy7cHq2HLptEV":"Common Area Electricity","fldAPU282Pp3dp9YW":["recF3zFKbY4wJ4P40"],"fld7TUYeH17YX6t0N":2026,"fldnEtJyU9t4Q91vq":"Budget","fldIngfMXZEpuSlVu":"Operating Expenses","fldJu5jjEXn4mMYSG":"Utilities","fldKCw72lO9e0WFuz":"6042","fldKtkY7NTlIHol07":"Direct Energy / Eversource","fldoKDNjWKF9G5QhM":8886.67,"fld6GLkqY33kT0nEr":-5459.58,"fld0laRIRvKrLgieR":5753.45,"fldQaEaLQpYkp02pC":-145.84,"fldRbPDZriXyBT0xk":-3216.84,"fldpLdJF85G236uWz":25379.58,"fldB978FBdF1cbkOz":15316,"fldv6nDF3xptGKP4p":6753.05,"fldv2HR9VxIAjDcMW":21126.33,"flddqJsbfKVRQ5bZa":29851.98,"fld0TUl79Wkn8iVBD":21645.05,"fldKW4xf1jkVzRwy0":14247.23}},{"fields":{"fldRAy7cHq2HLptEV":"Electric Consultant Fee","fldAPU282Pp3dp9YW":["recF3zFKbY4wJ4P40"],"fld7TUYeH17YX6t0N":2026,"fldnEtJyU9t4Q91vq":"Budget","fldIngfMXZEpuSlVu":"Operating Expenses","fldJu5jjEXn4mMYSG":"Utilities","fldKCw72lO9e0WFuz":"6043","fldKtkY7NTlIHol07":"OHIO SEMITRONICS CALIFORNIA / Greenwich Town","fldoKDNjWKF9G5QhM":92.5,"fld6GLkqY33kT0nEr":92.5,"fld0laRIRvKrLgieR":92.5,"fldQaEaLQpYkp02pC":92.5,"fldRbPDZriXyBT0xk":92.5,"fldpLdJF85G236uWz":92.5,"fldB978FBdF1cbkOz":92.5,"fldv6nDF3xptGKP4p":92.5,"fldv2HR9VxIAjDcMW":92.5,"flddqJsbfKVRQ5bZa":92.5,"fld0TUl79Wkn8iVBD":92.5,"fldKW4xf1jkVzRwy0":92.5}},{"fields":{"fldRAy7cHq2HLptEV":"Utilities - Gas","fldAPU282Pp3dp9YW":["recF3zFKbY4wJ4P40"],"fld7TUYeH17YX6t0N":2026,"fldnEtJyU9t4Q91vq":"Budget","fldIngfMXZEpuSlVu":"Operating Expenses","fldJu5jjEXn4mMYSG":"Utilities","fldKCw72lO9e0WFuz":"6050","fldKtkY7NTlIHol07":"","fldoKDNjWKF9G5QhM":1666.66,"fld6GLkqY33kT0nEr":1666.66,"fld0laRIRvKrLgieR":1666.66,"fldQaEaLQpYkp02pC":1666.66,"fldRbPDZriXyBT0xk":1666.66,"fldpLdJF85G236uWz":1666.66,"fldB978FBdF1cbkOz":1666.66,"fldv6nDF3xptGKP4p":1666.66,"fldv2HR9VxIAjDcMW":1666.66,"flddqJsbfKVRQ5bZa":1666.66,"fld0TUl79Wkn8iVBD":1666.66,"fldKW4xf1jkVzRwy0":1666.66}},{"fields":{"fldRAy7cHq2HLptEV":"Gas","fldAPU282Pp3dp9YW":["recF3zFKbY4wJ4P40"],"fld7TUYeH17YX6t0N":2026,"fldnEtJyU9t4Q91vq":"Budget","fldIngfMXZEpuSlVu":"Operating Expenses","fldJu5jjEXn4mMYSG":"Utilities","fldKCw72lO9e0WFuz":"6051","fldKtkY7NTlIHol07":"N/A","fldoKDNjWKF9G5QhM":1666.66,"fld6GLkqY33kT0nEr":1666.66,"fld0laRIRvKrLgieR":1666.66,"fldQaEaLQpYkp02pC":1666.66,"fldRbPDZriXyBT0xk":1666.66,"fldpLdJF85G236uWz":1666.66,"fldB978FBdF1cbkOz":1666.66,"fldv6nDF3xptGKP4p":1666.66,"fldv2HR9VxIAjDcMW":1666.66,"flddqJsbfKVRQ5bZa":1666.66,"fld0TUl79Wkn8iVBD":1666.66,"fldKW4xf1jkVzRwy0":1666.66}},{"fields":{"fldRAy7cHq2HLptEV":"Utilities - Water","fldAPU282Pp3dp9YW":["recF3zFKbY4wJ4P40"],"fld7TUYeH17YX6t0N":2026,"fldnEtJyU9t4Q91vq":"Budget","fldIngfMXZEpuSlVu":"Operating Expenses","fldJu5jjEXn4mMYSG":"Utilities","fldKCw72lO9e0WFuz":"6055","fldKtkY7NTlIHol07":"","fldoKDNjWKF9G5QhM":2012.5,"fld6GLkqY33kT0nEr":2012.5,"fld0laRIRvKrLgieR":2012.5,"fldQaEaLQpYkp02pC":2012.5,"fldRbPDZriXyBT0xk":2012.5,"fldpLdJF85G236uWz":2012.5,"fldB978FBdF1cbkOz":2012.5,"fldv6nDF3xptGKP4p":2012.5,"fldv2HR9VxIAjDcMW":2012.5,"flddqJsbfKVRQ5bZa":2012.5,"fld0TUl79Wkn8iVBD":2012.5,"fldKW4xf1jkVzRwy0":2012.5}},{"fields":{"fldRAy7cHq2HLptEV":"Water & Sewer","fldAPU282Pp3dp9YW":["recF3zFKbY4wJ4P40"],"fld7TUYeH17YX6t0N":2026,"fldnEtJyU9t4Q91vq":"Budget","fldIngfMXZEpuSlVu":"Operating Expenses","fldJu5jjEXn4mMYSG":"Utilities","fldKCw72lO9e0WFuz":"6056","fldKtkY7NTlIHol07":"N/A","fldoKDNjWKF9G5QhM":2012.5,"fld6GLkqY33kT0nEr":2012.5,"fld0laRIRvKrLgieR":2012.5,"fldQaEaLQpYkp02pC":2012.5,"fldRbPDZriXyBT0xk":2012.5,"fldpLdJF85G236uWz":2012.5,"fldB978FBdF1cbkOz":2012.5,"fldv6nDF3xptGKP4p":2012.5,"fldv2HR9VxIAjDcMW":2012.5,"flddqJsbfKVRQ5bZa":2012.5,"fld0TUl79Wkn8iVBD":2012.5,"fldKW4xf1jkVzRwy0":2012.5}}]