[{"fields":{"fldRAy7cHq2HLptEV":"Parking Lot Stenciling","fldAPU282Pp3dp9YW":["recF3zFKbY4wJ4P40"],"fld7TUYeH17YX6t0N":2026,"fldnEtJyU9t4Q91vq":"Budget","fldIngfMXZEpuSlVu":"Operating Expenses","fldJu5jjEXn4mMYSG":"Repairs & Maintenance","fldKCw72lO9e0WFuz":"5092","fldKtkY7NTlIHol07":"Applied Tech","fldB978FBdF1cbkOz":8000}},{"fields":{"fldRAy7cHq2HLptEV":"Key/Locks","fldAPU282Pp3dp9YW":["recF3zFKbY4wJ4P40"],"fld7TUYeH17YX6t0N":2026,"fldnEtJyU9t4Q91vq":"Budget","fldIngfMXZEpuSlVu":"Operating Expenses","fldJu5jjEXn4mMYSG":"Repairs & Maintenance","fldKCw72lO9e0WFuz":"5093","fldKtkY7NTlIHol07":"Main Lock","fldoKDNjWKF9G5QhM":62.5,"fld6GLkqY33kT0nEr":62.5,"fld0laRIRvKrLgieR":62.5,"fldQaEaLQpYkp02pC":62.5,"fldRbPDZriXyBT0xk":62.5,"fldpLdJF85G236uWz":62.5,"fldB978FBdF1cbkOz":62.5,"fldv6nDF3xptGKP4p":62.5,"fldv2HR9VxIAjDcMW":62.5,"flddqJsbfKVRQ5bZa":62.5,"fld0TUl79Wkn8iVBD":62.5,"fldKW4xf1jkVzRwy0":62.5}},{"fields":{"fldRAy7cHq2HLptEV":"Painting Supplies","fldAPU282Pp3dp9YW":["recF3zFKbY4wJ4P40"],"fld7TUYeH17YX6t0N":2026,"fldnEtJyU9t4Q91vq":"Budget","fldIngfMXZEpuSlVu":"Operating Expenses","fldJu5jjEXn4mMYSG":"Repairs & Maintenance","fldKCw72lO9e0WFuz":"5094","fldKtkY7NTlIHol07":"Home Depot","fldoKDNjWKF9G5QhM":540,"fld6GLkqY33kT0nEr":540,"fld0laRIRvKrLgieR":540,"fldQaEaLQpYkp02pC":540,"fldRbPDZriXyBT0xk":540,"fldpLdJF85G236uWz":540,"fldB978FBdF1cbkOz":540,"fldv6nDF3xptGKP4p":540,"fldv2HR9VxIAjDcMW":540,"flddqJsbfKVRQ5bZa":540,"fld0TUl79Wkn8iVBD":540,"fldKW4xf1jkVzRwy0":540}},{"fields":{"fldRAy7cHq2HLptEV":"Plumbing Supplies","fldAPU282Pp3dp9YW":["recF3zFKbY4wJ4P40"],"fld7TUYeH17YX6t0N":2026,"fldnEtJyU9t4Q91vq":"Budget","fldIngfMXZEpuSlVu":"Operating Expenses","fldJu5jjEXn4mMYSG":"Repairs & Maintenance","fldKCw72lO9e0WFuz":"5095","fldKtkY7NTlIHol07":"Various","fldoKDNjWKF9G5QhM":250,"fld6GLkqY33kT0nEr":250,"fld0laRIRvKrLgieR":250,"fldQaEaLQpYkp02pC":250,"fldRbPDZriXyBT0xk":250,"fldpLdJF85G236uWz":250,"fldB978FBdF1cbkOz":250,"fldv6nDF3xptGKP4p":250,"fldv2HR9VxIAjDcMW":250,"flddqJsbfKVRQ5bZa":250,"fld0TUl79Wkn8iVBD":250,"fldKW4xf1jkVzRwy0":250}},{"fields":{"fldRAy7cHq2HLptEV":"R&M - Misc Repairs","fldAPU282Pp3dp9YW":["recF3zFKbY4wJ4P40"],"fld7TUYeH17YX6t0N":2026,"fldnEtJyU9t4Q91vq":"Budget","fldIngfMXZEpuSlVu":"Operating Expenses","fldJu5jjEXn4mMYSG":"Repairs & Maintenance","fldKCw72lO9e0WFuz":"6000","fldKtkY7NTlIHol07":"","fldoKDNjWKF9G5QhM":760,"fld6GLkqY33kT0nEr":25260,"fld0laRIRvKrLgieR":4110,"fldQaEaLQpYkp02pC":1460,"fldRbPDZriXyBT0xk":2460,"fldpLdJF85G236uWz":1110,"fldB978FBdF1cbkOz":5014,"fldv6nDF3xptGKP4p":3760,"fldv2HR9VxIAjDcMW":1110,"flddqJsbfKVRQ5bZa":760,"fld0TUl79Wkn8iVBD":760,"fldKW4xf1jkVzRwy0":1110}},{"fields":{"fldRAy7cHq2HLptEV":"Plumbing Repairs","fldAPU282Pp3dp9YW":["recF3zFKbY4wJ4P40"],"fld7TUYeH17YX6t0N":2026,"fldnEtJyU9t4Q91vq":"Budget","fldIngfMXZEpuSlVu":"Operating Expenses","fldJu5jjEXn4mMYSG":"Repairs & Maintenance","fldKCw72lO9e0WFuz":"6001","fldKtkY7NTlIHol07":"T&M","fldoKDNjWKF9G5QhM":300,"fld6GLkqY33kT0nEr":24800,"fld0laRIRvKrLgieR":3650,"fldQaEaLQpYkp02pC":1000,"fldRbPDZriXyBT0xk":2000,"fldpLdJF85G236uWz":650,"fldB978FBdF1cbkOz":300,"fldv6nDF3xptGKP4p":300,"fldv2HR9VxIAjDcMW":650,"flddqJsbfKVRQ5bZa":300,"fld0TUl79Wkn8iVBD":300,"fldKW4xf1jkVzRwy0":650}},{"fields":{"fldRAy7cHq2HLptEV":"Electrical Repairs","fldAPU282Pp3dp9YW":["recF3zFKbY4wJ4P40"],"fld7TUYeH17YX6t0N":2026,"fldnEtJyU9t4Q91vq":"Budget","fldIngfMXZEpuSlVu":"Operating Expenses","fldJu5jjEXn4mMYSG":"Repairs & Maintenance","fldKCw72lO9e0WFuz":"6003","fldKtkY7NTlIHol07":"T&M","fldoKDNjWKF9G5QhM":460,"fld6GLkqY33kT0nEr":460,"fld0laRIRvKrLgieR":460,"fldQaEaLQpYkp02pC":460,"fldRbPDZriXyBT0xk":460,"fldpLdJF85G236uWz":460,"fldB978FBdF1cbkOz":4714,"fldv6nDF3xptGKP4p":3460,"fldv2HR9VxIAjDcMW":460,"flddqJsbfKVRQ5bZa":460,"fld0TUl79Wkn8iVBD":460,"fldKW4xf1jkVzRwy0":460}},{"fields":{"fldRAy7cHq2HLptEV":"R&M - Landscaping","fldAPU282Pp3dp9YW":["recF3zFKbY4wJ4P40"],"fld7TUYeH17YX6t0N":2026,"fldnEtJyU9t4Q91vq":"Budget","fldIngfMXZEpuSlVu":"Operating Expenses","fldJu5jjEXn4mMYSG":"Repairs & Maintenance","fldKCw72lO9e0WFuz":"","fldKtkY7NTlIHol07":"","fld0laRIRvKrLgieR":500,"fldQaEaLQpYkp02pC":7812,"fldRbPDZriXyBT0xk":25387,"fldpLdJF85G236uWz":24812,"fldB978FBdF1cbkOz":24212,"fldv6nDF3xptGKP4p":7812,"fldv2HR9VxIAjDcMW":7812,"flddqJsbfKVRQ5bZa":7812,"fld0TUl79Wkn8iVBD":7812}},{"fields":{"fldRAy7cHq2HLptEV":"Landscape Contract","fldAPU282Pp3dp9YW":["recF3zFKbY4wJ4P40"],"fld7TUYeH17YX6t0N":2026,"fldnEtJyU9t4Q91vq":"Budget","fldIngfMXZEpuSlVu":"Operating Expenses","fldJu5jjEXn4mMYSG":"Repairs & Maintenance","fldKCw72lO9e0WFuz":"6021","fldKtkY7NTlIHol07":"Finescape and Sons","fldQaEaLQpYkp02pC":7312,"fldRbPDZriXyBT0xk":7312,"fldpLdJF85G236uWz":7312,"fldB978FBdF1cbkOz":7312,"fldv6nDF3xptGKP4p":7312,"fldv2HR9VxIAjDcMW":7312,"flddqJsbfKVRQ5bZa":7312,"fld0TUl79Wkn8iVBD":7312}},{"fields":{"fldRAy7cHq2HLptEV":"Seasonal Flowers","fldAPU282Pp3dp9YW":["recF3zFKbY4wJ4P40"],"fld7TUYeH17YX6t0N":2026,"fldnEtJyU9t4Q91vq":"Budget","fldIngfMXZEpuSlVu":"Operating Expenses","fldJu5jjEXn4mMYSG":"Repairs & Maintenance","fldKCw72lO9e0WFuz":"6022","fldKtkY7NTlIHol07":"Finescape and Sons","fld0laRIRvKrLgieR":500,"fldQaEaLQpYkp02pC":500,"fldRbPDZriXyBT0xk":8500,"fldpLdJF85G236uWz":12500,"fldB978FBdF1cbkOz":500,"fldv6nDF3xptGKP4p":500,"fldv2HR9VxIAjDcMW":500,"flddqJsbfKVRQ5bZa":500,"fld0TUl79Wkn8iVBD":500}}]